MANIFEST.in
README.md
setup.py
karelpy/__init__.py
karelpy/beeper.py
karelpy/config.py
karelpy/dot.py
karelpy/ikarel.py
karelpy/karel.py
karelpy/wall.py
karelpy/world.py
karelpy.egg-info/PKG-INFO
karelpy.egg-info/SOURCES.txt
karelpy.egg-info/dependency_links.txt
karelpy.egg-info/not-zip-safe
karelpy.egg-info/requires.txt
karelpy.egg-info/top_level.txt
karelpy/world/beeper.png
karelpy/world/karel.png
karelpy/world/one.w
karelpy/world/two.w