Metadata-Version: 1.1
Name: karelpy
Version: 0.1
Summary: Popular educational coding robot
Home-page: http://github.com/haksoat/karelpy
Author: Habeeb Shopeju
Author-email: shopejuh@gmail.com
License: MIT
Keywords: karel robot education
Platform: UNKNOWN
Classifier: License :: OSI Approved :: BSD License
Classifier: Development Status :: 3 - Alpha
Classifier: Programming Language :: Python :: 3.6
Classifier: Topic :: Education :: Computer Aided Instruction (CAI)
